jinja24doc/__init__.py
jinja24doc/apidoc.py
jinja24doc/context.py
jinja24doc/frontend.py
jinja24doc/rst.py
jinja24doc/tools.py
jinja24doc/wiki.py
jinja24doc-1.3.4.data/data/share/doc/jinja24doc/ChangeLog
jinja24doc-1.3.4.data/data/share/doc/jinja24doc/LICENCE
jinja24doc-1.3.4.data/data/share/doc/jinja24doc/README.rst
jinja24doc-1.3.4.data/data/share/doc/jinja24doc/templates.rst
jinja24doc-1.3.4.data/data/share/doc/jinja24doc/tools.rst
jinja24doc-1.3.4.data/data/share/doc/jinja24doc/html/api.html
jinja24doc-1.3.4.data/data/share/doc/jinja24doc/html/index.html
jinja24doc-1.3.4.data/data/share/doc/jinja24doc/html/licence.html
jinja24doc-1.3.4.data/data/share/doc/jinja24doc/html/small-logo.png
jinja24doc-1.3.4.data/data/share/doc/jinja24doc/html/style.css
jinja24doc-1.3.4.data/data/share/doc/jinja24doc/html/templates.html
jinja24doc-1.3.4.data/data/share/doc/jinja24doc/html/tools.html
jinja24doc-1.3.4.data/data/share/doc/jinja24doc/html/web.css
jinja24doc-1.3.4.data/data/share/jinja24doc/templates/_footer.html
jinja24doc-1.3.4.data/data/share/jinja24doc/templates/_header.html
jinja24doc-1.3.4.data/data/share/jinja24doc/templates/_reference.html
jinja24doc-1.3.4.data/data/share/jinja24doc/templates/_simple.html
jinja24doc-1.3.4.data/data/share/jinja24doc/templates/_simple_with_submodules.html
jinja24doc-1.3.4.data/data/share/jinja24doc/templates/_source.html
jinja24doc-1.3.4.data/data/share/jinja24doc/templates/_text.html
jinja24doc-1.3.4.data/data/share/jinja24doc/templates/blue.css
jinja24doc-1.3.4.data/data/share/jinja24doc/templates/gray.css
jinja24doc-1.3.4.data/data/share/jinja24doc/templates/green.css
jinja24doc-1.3.4.data/data/share/jinja24doc/templates/inverse.css
jinja24doc-1.3.4.data/data/share/jinja24doc/templates/module.html
jinja24doc-1.3.4.data/data/share/jinja24doc/templates/red.css
jinja24doc-1.3.4.data/data/share/jinja24doc/templates/style.css
jinja24doc-1.3.4.data/data/share/jinja24doc/templates/text.html
jinja24doc-1.3.4.dist-info/LICENCE
jinja24doc-1.3.4.dist-info/METADATA
jinja24doc-1.3.4.dist-info/WHEEL
jinja24doc-1.3.4.dist-info/entry_points.txt
jinja24doc-1.3.4.dist-info/top_level.txt
jinja24doc-1.3.4.dist-info/RECORD
