Metadata-Version: 2.1
Name: jinja24doc
Version: 1.3.4
Summary: Jinja24Doc for Python
Home-page: http://poorhttp.zeropage.cz/jinja24doc
Author: Ondrej Tuma
Author-email: mcbig@zeropage.cz
License: BSD
Platform: UNKNOWN
Classifier: Development Status :: 5 - Production/Stable
Classifier: Environment :: Console
Classifier: Intended Audience :: Developers
Classifier: License :: OSI Approved :: BSD License
Classifier: Natural Language :: English
Classifier: Natural Language :: Czech
Classifier: Operating System :: POSIX
Classifier: Programming Language :: Python :: 2
Classifier: Programming Language :: Python :: 3
Classifier: Topic :: Documentation
Classifier: Topic :: Software Development :: Documentation
Classifier: Topic :: Text Processing :: Markup
Classifier: Topic :: Utilities
Requires-Dist: jinja2 (>=2.10)
Requires-Dist: docutils-tinyhtmlwriter
Requires-Dist: pygments
